dila/__init__.py
dila/alembic.ini
dila/config.py
dila/application/__init__.py
dila/application/authentication.py
dila/application/languages.py
dila/application/meta.py
dila/application/po_entry_savers.py
dila/application/resources.py
dila/application/structures.py
dila/application/translations.py
dila/data/__init__.py
dila/data/base_strings.py
dila/data/engine.py
dila/data/languages.py
dila/data/po_metadata.py
dila/data/resources.py
dila/data/translated_strings.py
dila/data/alembic/__init__.py
dila/data/alembic/env.py
dila/data/alembic/versions/04d870437e14_add_resource_name.py
dila/data/alembic/versions/0ab02337f372_add_translated_strings.py
dila/data/alembic/versions/4ce05ae50d01_add_on_delete_cascade_to_postgres.py
dila/data/alembic/versions/558950f05825_add_base_string_unique_constraint.py
dila/data/alembic/versions/58e7f2fc7ff7_set_translations_not_null.py
dila/data/alembic/versions/71f4f6391672_add_plural_base_string.py
dila/data/alembic/versions/7742ac8b1599_add_languages.py
dila/data/alembic/versions/85e1d78ef077_add_po_metadata.py
dila/data/alembic/versions/__init__.py
dila/data/alembic/versions/deb5c1dad94a_add_plural_translations.py
dila/data/alembic/versions/e183d3958ae0_split_translated_strings.py
dila/data/alembic/versions/f8927e919732_add_resource_model.py
dila/frontend/__init__.py
dila/frontend/cli.py
dila/frontend/initialize.py
dila/frontend/flask/__init__.py
dila/frontend/flask/authenticate_views.py
dila/frontend/flask/forms.py
dila/frontend/flask/languages.py
dila/frontend/flask/template_tools.py
dila/frontend/flask/user_tools.py
dila/frontend/flask/views.py
dila/frontend/flask/wsgi.py
dila/frontend/flask/static/vendor/css/bootstrap.min.css
dila/frontend/flask/static/vendor/js/bootstrap.min.js
dila/frontend/flask/static/vendor/js/jquery.min.js
dila/frontend/flask/templates/home.html
dila/frontend/flask/templates/layout.html
dila/frontend/flask/templates/login.html
dila-0.4.3.dist-info/DESCRIPTION.rst
dila-0.4.3.dist-info/METADATA
dila-0.4.3.dist-info/RECORD
dila-0.4.3.dist-info/WHEEL
dila-0.4.3.dist-info/entry_points.txt
dila-0.4.3.dist-info/metadata.json
dila-0.4.3.dist-info/top_level.txt
