Metadata-Version: 2.0
Name: dila
Version: 0.4.3
Summary: Dila is a open source web-based translation platform for translators, content creators and developers.
Home-page: https://github.com/socialwifi/dila
Author: Jakub Skiepko
Author-email: it@socialwifi.com
License: BSD
Platform: UNKNOWN
Classifier: Development Status :: 5 - Production/Stable
Classifier: Environment :: Console
Classifier: Intended Audience :: Developers
Classifier: License :: OSI Approved :: BSD License
Classifier: Operating System :: OS Independent
Classifier: Programming Language :: Python
Classifier: Programming Language :: Python :: 3
Classifier: Programming Language :: Python :: 3.6
Requires-Dist: alembic
Requires-Dist: cached-property
Requires-Dist: cmd2
Requires-Dist: Flask
Requires-Dist: Flask-WTF
Requires-Dist: polib
Requires-Dist: psycopg2
Requires-Dist: pyldap
Requires-Dist: SQLAlchemy
Requires-Dist: sqlalchemy-postgres-autocommit
